sorted/__init__.py
sorted/base.py
sorted/sorted.py
sorted/subtract.py
sorted/unique.py
sorted-0.1.0.dist-info/METADATA
sorted-0.1.0.dist-info/WHEEL
sorted-0.1.0.dist-info/top_level.txt
sorted-0.1.0.dist-info/RECORD
