Metadata-Version: 2.1
Name: sorted
Version: 0.1.0
Summary: Merge, subtract, deduplicate and otherwise manipulate Python iterators that are known to be sorted.
Home-page: https://github.com/anatoly-scherbakov/sorted
Author: Anatoly Scherbakov
Author-email: altaisoft@gmail.com
License: MIT
Platform: UNKNOWN
Classifier: Programming Language :: Python :: 3
Classifier: Programming Language :: Python :: 3.7
Classifier: License :: OSI Approved :: MIT License
Classifier: Operating System :: OS Independent
Provides-Extra: dev
Requires-Dist: pytest ; extra == 'dev'
Requires-Dist: coverage ; extra == 'dev'
Requires-Dist: mypy ; extra == 'dev'
Requires-Dist: black ; extra == 'dev'
Requires-Dist: twine ; extra == 'dev'
